CHANGES.txt
README.txt
setup.py
collective/__init__.py
collective.collage.windowz.egg-info/PKG-INFO
collective.collage.windowz.egg-info/SOURCES.txt
collective.collage.windowz.egg-info/dependency_links.txt
collective.collage.windowz.egg-info/namespace_packages.txt
collective.collage.windowz.egg-info/not-zip-safe
collective.collage.windowz.egg-info/requires.txt
collective.collage.windowz.egg-info/top_level.txt
collective/collage/__init__.py
collective/collage/windowz/__init__.py
collective/collage/windowz/browser.py
collective/collage/windowz/configure.zcml
collective/collage/windowz/standard.pt